vlaamscodex_autoload.pth
dialects/README.md
dialects/index.json
dialects/schema.md
dialects/packs/nl__standard.json
dialects/packs/vlaams__aalst.json
dialects/packs/vlaams__aarschot.json
dialects/packs/vlaams__antwerps.json
dialects/packs/vlaams__antwerpse-ommeland.json
dialects/packs/vlaams__asse.json
dialects/packs/vlaams__basis.json
dialects/packs/vlaams__beveren.json
dialects/packs/vlaams__bilzen.json
dialects/packs/vlaams__blankenberge.json
dialects/packs/vlaams__brabants.json
dialects/packs/vlaams__bree.json
dialects/packs/vlaams__brugge.json
dialects/packs/vlaams__brussels.json
dialects/packs/vlaams__brusselse-ommeland.json
dialects/packs/vlaams__dendermonde.json
dialects/packs/vlaams__denderstreek-noord.json
dialects/packs/vlaams__denderstreek-zuid.json
dialects/packs/vlaams__denderstreek.json
dialects/packs/vlaams__diest.json
dialects/packs/vlaams__diksmuide.json
dialects/packs/vlaams__eeklo.json
dialects/packs/vlaams__geel.json
dialects/packs/vlaams__genk.json
dialects/packs/vlaams__gent.json
dialects/packs/vlaams__gentse-ommeland.json
dialects/packs/vlaams__hageland.json
dialects/packs/vlaams__halle.json
dialects/packs/vlaams__hasselt.json
dialects/packs/vlaams__herentals.json
dialects/packs/vlaams__heuvelland.json
dialects/packs/vlaams__ieper.json
dialects/packs/vlaams__kempen.json
dialects/packs/vlaams__knokke-heist.json
dialects/packs/vlaams__kortrijk.json
dialects/packs/vlaams__leiestreek.json
dialects/packs/vlaams__leuven.json
dialects/packs/vlaams__leuvense-ommeland.json
dialects/packs/vlaams__lier.json
dialects/packs/vlaams__limburgs.json
dialects/packs/vlaams__lokeren.json
dialects/packs/vlaams__maaseik.json
dialects/packs/vlaams__maasland.json
dialects/packs/vlaams__maasmechelen.json
dialects/packs/vlaams__maldegem.json
dialects/packs/vlaams__mechelen.json
dialects/packs/vlaams__meetjesland-noord.json
dialects/packs/vlaams__meetjesland-zuid.json
dialects/packs/vlaams__meetjesland.json
dialects/packs/vlaams__menen.json
vlaamscodex-0.2.5.dist-info/licenses/LICENSE
vlaamscodex-0.2.5.dist-info/METADATA
vlaamscodex-0.2.5.dist-info/WHEEL
vlaamscodex-0.2.5.dist-info/entry_points.txt
vlaamscodex-0.2.5.dist-info/top_level.txt
vlaamscodex-0.2.5.dist-info/RECORD
