Metadata-Version: 2.4
Name: vlaamscodex
Version: 0.2.5
Summary: A transpiler toolchain for Platskript, a programming language using Multi-Vlaams dialect keywords that compiles to Python
Author: VlaamsCodex contributors
Maintainer-email: Anubis <anubissbe@users.noreply.github.com>
License-Expression: MIT
Project-URL: Homepage, https://github.com/brentishere41848/Vlaams-Codex
Project-URL: Documentation, https://github.com/brentishere41848/Vlaams-Codex#readme
Project-URL: Repository, https://github.com/brentishere41848/Vlaams-Codex.git
Project-URL: Changelog, https://github.com/brentishere41848/Vlaams-Codex/blob/main/CHANGELOG.md
Project-URL: Bug Tracker, https://github.com/brentishere41848/Vlaams-Codex/issues
Project-URL: Source Code, https://github.com/brentishere41848/Vlaams-Codex
Keywords: transpiler,compiler,flemish,dutch,dialect,programming-language,dsl,python,codec,platskript,vlaams,belgium,educational,multi-vlaams,west-vlaams,antwerps,limburgs,brussels,repl,interactive
Classifier: Development Status :: 4 - Beta
Classifier: Environment :: Console
Classifier: Intended Audience :: Developers
Classifier: Intended Audience :: Education
Classifier: Natural Language :: Dutch
Classifier: Operating System :: OS Independent
Classifier: Programming Language :: Python
Classifier: Programming Language :: Python :: 3
Classifier: Programming Language :: Python :: 3.10
Classifier: Programming Language :: Python :: 3.11
Classifier: Programming Language :: Python :: 3.12
Classifier: Programming Language :: Python :: 3.13
Classifier: Programming Language :: Python :: 3 :: Only
Classifier: Programming Language :: Other
Classifier: Topic :: Software Development :: Compilers
Classifier: Topic :: Software Development :: Interpreters
Classifier: Topic :: Software Development :: Code Generators
Classifier: Topic :: Education
Classifier: Topic :: Text Processing :: Linguistic
Classifier: Typing :: Typed
Requires-Python: >=3.10
License-File: LICENSE
Provides-Extra: dev
Requires-Dist: pytest>=7; extra == "dev"
Requires-Dist: build>=1; extra == "dev"
Dynamic: license-file
